youtube_search_requests/__init__.py
youtube_search_requests/__main__.py
youtube_search_requests/async_search.py
youtube_search_requests/async_session.py
youtube_search_requests/constants.py
youtube_search_requests/search.py
youtube_search_requests/session.py
youtube_search_requests/extractor/__init__.py
youtube_search_requests/extractor/async_extractors.py
youtube_search_requests/extractor/extractors.py
youtube_search_requests/parser/__init__.py
youtube_search_requests/parser/constants.py
youtube_search_requests/parser/continuation_token.py
youtube_search_requests/parser/related_video_data.py
youtube_search_requests/parser/video_data.py
youtube_search_requests/utils/__init__.py
youtube_search_requests/utils/errors.py
youtube_search_requests-0.1.20.dist-info/LICENSE
youtube_search_requests-0.1.20.dist-info/METADATA
youtube_search_requests-0.1.20.dist-info/WHEEL
youtube_search_requests-0.1.20.dist-info/entry_points.txt
youtube_search_requests-0.1.20.dist-info/top_level.txt
youtube_search_requests-0.1.20.dist-info/RECORD
