Metadata-Version: 2.1
Name: youtube-search-requests
Version: 0.1.20
Summary: Search Youtube videos using python requests without Youtube API
Home-page: https://github.com/trollfist20/youtube-search-requests
Author: Rahman Yusuf
Author-email: danipart4@gmail.com
License: MIT
Download-URL: https://github.com/trollfist20/youtube-search-requests/archive/v0.1.20.tar.gz
Keywords: youtube,youtube-search
Platform: UNKNOWN
Classifier: Development Status :: 5 - Production/Stable
Classifier: Intended Audience :: Developers
Classifier: Topic :: Software Development :: Build Tools
Classifier: License :: OSI Approved :: MIT License
Classifier: Programming Language :: Python :: 3 :: Only
Classifier: Programming Language :: Python :: 3
Classifier: Programming Language :: Python :: 3.5
Classifier: Programming Language :: Python :: 3.6
Classifier: Programming Language :: Python :: 3.7
Classifier: Programming Language :: Python :: 3.8
Requires-Dist: requests
Requires-Dist: aiohttp
